Workbook

Sheet Лист1
A1: Показатель | B1: Обозначение | C1: Ед. изм. | D1: Значение
A2: Количество сотрудников, работающих с документами | B2: – | C2: чел. | D2: 320 | I2: Годовые эксплуатационные затраты при ручной обработке (ОС1) | J2: =(D3*D4/D6)*(1+D7)*(1+D8)*12 -> 1378472.7
A3: Средняя месячная зарплата сотрудника | B3: Z | C3: руб. | D3: 90000 | I3: Годовые эксплуатационные затраты после внедрения СЭД (ОС2)
A4: Затраты времени на ручную обработку (до внедрения) | B4: T1 | C4: дней/мес | D4: 18 | I4: Затраты машинного времени (С1) | J4: =12*D9*D10 -> 10800
A5: Затраты времени после внедрения СЭД | B5: T2 | C5: дней/мес | D5: 9 | I5: Затраты ручного труда после внедрения (С2) | J5: =D3*D5*(1+D7)*(1+D8)*12/D6 -> 689236.36
A6: Среднее количество рабочих дней в месяце | B6: Q | C6: дней | D6: 22 | I6: Затраты на обучение и настройку (С3)
A7: Коэффициент накладных расходов | B7: α | C7: – | D7: 0.2 | I7: зарплата на обучение (К31) | J7: =D3*D11*(1+D7)*(1+D8)*12/D6 -> 765818.18
A8: Коэффициент дополнительной зарплаты (отчисления) | B8: β | C8: – | D8: 0.3 | I8: машинное время на обучение (К32) | J8: =12*D9*D11 -> 7200
A9: Себестоимость часа работы ПЭВМ | B9: Sq | C9: руб./час | D9: 60 | I9: прочие расходы (К33) | J9: =(J7+J8)*D13 -> 77301.818
A10: Время работы ПЭВМ после внедрения (месяц) | B10: Tq | C10: час/мес | D10: 15 | I10: K3 | J10: =J7+J8+J9 -> 850320
A11: Время работы ПЭВМ на обучение (месяц) | B11: Tq2 | C11: час/мес | D11: 10 | I11: C3 | J11: =J10*D12 -> 85032
A12: Коэффициент настройки оборудования | B12: γ | C12: – | D12: 0.1 | I12: ОС2 | J12: =J4+J5+J11 -> 785068.36
A13: Коэффициент прочих расходов | B13: h | C13: – | D13: 0.1 | I13: Годовая экономия (S) | J13: =J2-J12 -> 593404.36
A14: Нормативный коэффициент эффективности (Е_nce) | B14: Еnce | C14: – | D14: 0.3 | I14: Коэффициент экономической эффективности (Er) | J14: =J13/D15 -> 0.23736175
A15: Единовременные затраты на внедрение СЭД (К) | B15: К | C15: руб. | D15: 2500000 | I15: Срок окупаемости (T) | J15: =D15/J13 -> 4.2129788 | K15: =ROUNDUP(J15*12,0) -> 51 | L15: месяц
A16: Ставка дисконтирования | B16: r | C16: % | D16: 0.1
A17: Годовая экономия от снижения штрафов/потерь | B17: Pk | C17: руб./год | D17: 400000
A18: Срок реализации проекта | B18: n | C18: лет | D18: 3
I20: Годовой денежный поток (Pk) | J20: =D17+J13 -> 993404.36
I21: Чистая приведённая стоимость (NPV) | J21: =(J20/((1+D16)^1))+(J20/((1+D16)^2))+(J20/((1+D16)^3))+(J20/((1+D16)^4))-D15 -> 648958.17
I22: Индекс рентабельности (PI) | J22: =((J20/((1+D16)^1))+(J20/((1+D16)^2))+(J20/((1+D16)^3))+(J20/((1+D16)^4)))/D15 -> 1.2595833

Sheet IRR
A1: 0.05 | B1: =Лист1!$J$20/((1+IRR!A1)^1)+Лист1!$J$20/((1+IRR!A1)^2)+Лист1!$J$20/((1+IRR!A1)^3)+Лист1!$J$20/((1+IRR!A1)^4)-Лист1!$D$15 -> 1022562.7
A2: 0.1 | B2: =Лист1!$J$20/((1+IRR!A2)^1)+Лист1!$J$20/((1+IRR!A2)^2)+Лист1!$J$20/((1+IRR!A2)^3)+Лист1!$J$20/((1+IRR!A2)^4)-Лист1!$D$15 -> 648958.17
A3: 0.15 | B3: =Лист1!$J$20/((1+IRR!A3)^1)+Лист1!$J$20/((1+IRR!A3)^2)+Лист1!$J$20/((1+IRR!A3)^3)+Лист1!$J$20/((1+IRR!A3)^4)-Лист1!$D$15 -> 336147.96
A4: 0.2 | B4: =Лист1!$J$20/((1+IRR!A4)^1)+Лист1!$J$20/((1+IRR!A4)^2)+Лист1!$J$20/((1+IRR!A4)^3)+Лист1!$J$20/((1+IRR!A4)^4)-Лист1!$D$15 -> 71660.216
A5: 0.25 | B5: =Лист1!$J$20/((1+IRR!A5)^1)+Лист1!$J$20/((1+IRR!A5)^2)+Лист1!$J$20/((1+IRR!A5)^3)+Лист1!$J$20/((1+IRR!A5)^4)-Лист1!$D$15 -> -153976.25
A6: 0.3 | B6: =Лист1!$J$20/((1+IRR!A6)^1)+Лист1!$J$20/((1+IRR!A6)^2)+Лист1!$J$20/((1+IRR!A6)^3)+Лист1!$J$20/((1+IRR!A6)^4)-Лист1!$D$15 -> -348047.06
A7: 0.35 | B7: =Лист1!$J$20/((1+IRR!A7)^1)+Лист1!$J$20/((1+IRR!A7)^2)+Лист1!$J$20/((1+IRR!A7)^3)+Лист1!$J$20/((1+IRR!A7)^4)-Лист1!$D$15 -> -516223.22
A8: 0.4 | B8: =Лист1!$J$20/((1+IRR!A8)^1)+Лист1!$J$20/((1+IRR!A8)^2)+Лист1!$J$20/((1+IRR!A8)^3)+Лист1!$J$20/((1+IRR!A8)^4)-Лист1!$D$15 -> -662967.36
A9: 0.45 | B9: =Лист1!$J$20/((1+IRR!A9)^1)+Лист1!$J$20/((1+IRR!A9)^2)+Лист1!$J$20/((1+IRR!A9)^3)+Лист1!$J$20/((1+IRR!A9)^4)-Лист1!$D$15 -> -791826.7
A10: 0.5 | B10: =Лист1!$J$20/((1+IRR!A10)^1)+Лист1!$J$20/((1+IRR!A10)^2)+Лист1!$J$20/((1+IRR!A10)^3)+Лист1!$J$20/((1+IRR!A10)^4)-Лист1!$D$15 -> -905647.32
A11: 0.55 | B11: =Лист1!$J$20/((1+IRR!A11)^1)+Лист1!$J$20/((1+IRR!A11)^2)+Лист1!$J$20/((1+IRR!A11)^3)+Лист1!$J$20/((1+IRR!A11)^4)-Лист1!$D$15 -> -1006732.6
A12: 0.6 | B12: =Лист1!$J$20/((1+IRR!A12)^1)+Лист1!$J$20/((1+IRR!A12)^2)+Лист1!$J$20/((1+IRR!A12)^3)+Лист1!$J$20/((1+IRR!A12)^4)-Лист1!$D$15 -> -1096961.9
... A18: 0.9 | B18: =Лист1!$J$20/((1+IRR!A18)^1)+Лист1!$J$20/((1+IRR!A18)^2)+Лист1!$J$20/((1+IRR!A18)^3)+Лист1!$J$20/((1+IRR!A18)^4)-Лист1!$D$15 -> -1480914.6
A19: 0.95 | B19: =Лист1!$J$20/((1+IRR!A19)^1)+Лист1!$J$20/((1+IRR!A19)^2)+Лист1!$J$20/((1+IRR!A19)^3)+Лист1!$J$20/((1+IRR!A19)^4)-Лист1!$D$15 -> -1526632.1 | I19: IRR | J19: 0.21505
A20: 1 | B20: =Лист1!$J$20/((1+IRR!A20)^1)+Лист1!$J$20/((1+IRR!A20)^2)+Лист1!$J$20/((1+IRR!A20)^3)+Лист1!$J$20/((1+IRR!A20)^4)-Лист1!$D$15 -> -1568683.4
